epik8s_tools/__init__.py
epik8s_tools/epik8s_common.py
epik8s_tools/epik8s_compose.py
epik8s_tools/epik8s_gen.py
epik8s_tools/epik8s_run.py
epik8s_tools/opigen.py
epik8s_tools/template/README.md
epik8s_tools/template/deploy.yaml
epik8s_tools/template/epik8s.yaml
epik8s_tools/template/nfsmount.sh.j2
epik8s_tools/template/settings.ini
epik8s_tools/template/values.yaml
epik8s_tools/template/applications/icpdasim/config.json
epik8s_tools/template/iocs/ibilt.yaml.j2
epik8s_tools/template/iocs/agilent-vac/agilent-vac.yaml.j2
epik8s_tools/template/iocs/caenels/caenels.yaml.j2
epik8s_tools/template/iocs/camera/camera_template.yaml.j2
epik8s_tools/template/iocs/icpdas/icpdas_template.yaml.j2
epik8s_tools/template/iocs/motor/motor.yaml.j2
epik8s_tools/template/iocs/sigmaphi/sigmaphi.yaml.j2
epik8s_tools/template/services/gateway/gwaccess.access
epik8s_tools/template/services/gateway/pvlist
epik8s_tools/template/services/gateway/start.sh
epik8s_tools/template/services/pvagateway/gwaccess.access
epik8s_tools/template/services/pvagateway/pvlist
epik8s_tools/template/services/pvagateway/start.sh
epik8s_tools-0.9.15.dist-info/METADATA
epik8s_tools-0.9.15.dist-info/WHEEL
epik8s_tools-0.9.15.dist-info/entry_points.txt
epik8s_tools-0.9.15.dist-info/top_level.txt
epik8s_tools-0.9.15.dist-info/RECORD
