Metadata-Version: 2.4
Name: epik8s-tools
Version: 0.9.15
Summary: A set of tools for generating Kubernetes Helm charts for EPICS-based systems.
Home-page: https://github.com/yourusername/epik8s-tools
Author: Andrea Michelotti
Author-email: andrea.michelotti@infn.it
Classifier: Programming Language :: Python :: 3
Classifier: License :: OSI Approved :: MIT License
Classifier: Operating System :: OS Independent
Requires-Python: >=3.10
Requires-Dist: pyyaml
Requires-Dist: Jinja2
Requires-Dist: phoebusgen
Requires-Dist: jnjrender
Dynamic: author
Dynamic: author-email
Dynamic: classifier
Dynamic: description
Dynamic: description-content-type
Dynamic: home-page
Dynamic: requires-dist
Dynamic: requires-python
Dynamic: summary
